dcekit/__init__.py
dcekit/design_of_exmeriments/__init__.py
dcekit/design_of_exmeriments/bayesian_optimization.py
dcekit/generative_model/__init__.py
dcekit/generative_model/gmr.py
dcekit/generative_model/gtm.py
dcekit/generative_model/vbgmr.py
dcekit/just_in_time/__init__.py
dcekit/just_in_time/jitpls.py
dcekit/just_in_time/lwpls.py
dcekit/learning/__init__.py
dcekit/learning/ensemble_learning.py
dcekit/learning/semi_supervised_learning.py
dcekit/learning/transfer_learning.py
dcekit/optimization/__init__.py
dcekit/optimization/fast_opt_svr_hyperparams.py
dcekit/optimization/iot.py
dcekit/optimization/opt_dnn_hyperparams.py
dcekit/optimization/opt_dnn_hyperparams_class.py
dcekit/sampling/__init__.py
dcekit/sampling/kennard_stone.py
dcekit/validation/__init__.py
dcekit/validation/applicability_domain.py
dcekit/validation/metrics.py
dcekit/validation/validation.py
dcekit/variable_selection/__init__.py
dcekit/variable_selection/basic_variable_selection.py
dcekit/variable_selection/local_interpretation.py
dcekit/variable_selection/variable_importance.py
dcekit-2.14.2.dist-info/LICENSE
dcekit-2.14.2.dist-info/LICENSE.txt
dcekit-2.14.2.dist-info/METADATA
dcekit-2.14.2.dist-info/WHEEL
dcekit-2.14.2.dist-info/top_level.txt
dcekit-2.14.2.dist-info/RECORD
