Metadata-Version: 2.2
Name: dcekit
Version: 2.14.2
Summary: Data Chemical Engineering toolkit
Home-page: https://github.com/hkaneko1985/dcekit/
Author: Hiromasa Kaneko
Author-email: hkaneko226@gmail.com
License: MIT License
License-File: LICENSE
License-File: LICENSE.txt
Requires-Dist: numpy
Requires-Dist: pandas
Requires-Dist: scikit-learn
Requires-Dist: scipy
Dynamic: author
Dynamic: author-email
Dynamic: description
Dynamic: home-page
Dynamic: license
Dynamic: requires-dist
Dynamic: summary
